llama_index/tools/linkup_research/__init__.py
llama_index/tools/linkup_research/base.py
llama_index_tools_linkup_research-0.4.1.dist-info/METADATA
llama_index_tools_linkup_research-0.4.1.dist-info/WHEEL
llama_index_tools_linkup_research-0.4.1.dist-info/licenses/LICENSE
llama_index_tools_linkup_research-0.4.1.dist-info/RECORD
