Metadata-Version: 2.4
Name: llama-index-tools-linkup-research
Version: 0.4.1
Summary: llama-index tools linkup_research integration
Author-email: Your Name <you@example.com>
Maintainer: juliette0704
License-Expression: MIT
License-File: LICENSE
Keywords: search
Requires-Python: <4.0,>=3.9
Requires-Dist: linkup-sdk>=0.2.2
Requires-Dist: llama-index-core<0.15,>=0.13.0
